ApachecnJavawebZhPt3/404.html
ApachecnJavawebZhPt3/CNAME
ApachecnJavawebZhPt3/Dockerfile
ApachecnJavawebZhPt3/LICENSE
ApachecnJavawebZhPt3/LICENSE_ETC
ApachecnJavawebZhPt3/NAV.md
ApachecnJavawebZhPt3/README.md
ApachecnJavawebZhPt3/SUMMARY.md
ApachecnJavawebZhPt3/__init__.py
ApachecnJavawebZhPt3/__main__.py
ApachecnJavawebZhPt3/index.html
ApachecnJavawebZhPt3/update.sh
ApachecnJavawebZhPt3/asset/LXGWWenKaiScreen.ttf
ApachecnJavawebZhPt3/asset/__init__.py
ApachecnJavawebZhPt3/asset/back-to-top.css
ApachecnJavawebZhPt3/asset/back-to-top.js
ApachecnJavawebZhPt3/asset/dark-mode.css
ApachecnJavawebZhPt3/asset/dark-mode.js
ApachecnJavawebZhPt3/asset/docsify-apachecn-footer.js
ApachecnJavawebZhPt3/asset/docsify-baidu-push.js
ApachecnJavawebZhPt3/asset/docsify-baidu-stat.js
ApachecnJavawebZhPt3/asset/docsify-clicker.js
ApachecnJavawebZhPt3/asset/docsify-cnzz.js
ApachecnJavawebZhPt3/asset/docsify-copy-code.min.js
ApachecnJavawebZhPt3/asset/docsify-katex.js
ApachecnJavawebZhPt3/asset/docsify-quick-page.css
ApachecnJavawebZhPt3/asset/docsify-quick-page.js
ApachecnJavawebZhPt3/asset/docsify-sidebar-collapse.min.js
ApachecnJavawebZhPt3/asset/docsify.min.js
ApachecnJavawebZhPt3/asset/edit.css
ApachecnJavawebZhPt3/asset/edit.js
ApachecnJavawebZhPt3/asset/edit.svg
ApachecnJavawebZhPt3/asset/flygon_qr_alipay.png
ApachecnJavawebZhPt3/asset/katex.min.css
ApachecnJavawebZhPt3/asset/left.svg
ApachecnJavawebZhPt3/asset/lxgw-wenkai.css
ApachecnJavawebZhPt3/asset/moon.svg
ApachecnJavawebZhPt3/asset/prism-c.min.js
ApachecnJavawebZhPt3/asset/prism-cpp.min.js
ApachecnJavawebZhPt3/asset/prism-csharp.min.js
ApachecnJavawebZhPt3/asset/prism-darcula.css
ApachecnJavawebZhPt3/asset/prism-java.min.js
ApachecnJavawebZhPt3/asset/prism-javascript.min.js
ApachecnJavawebZhPt3/asset/prism-php.min.js
ApachecnJavawebZhPt3/asset/prism-python.min.js
ApachecnJavawebZhPt3/asset/right.svg
ApachecnJavawebZhPt3/asset/search.min.js
ApachecnJavawebZhPt3/asset/share.css
ApachecnJavawebZhPt3/asset/share.js
apachecn_javaweb_zh_pt3-2022.10.16.0.dist-info/METADATA
apachecn_javaweb_zh_pt3-2022.10.16.0.dist-info/WHEEL
apachecn_javaweb_zh_pt3-2022.10.16.0.dist-info/entry_points.txt
apachecn_javaweb_zh_pt3-2022.10.16.0.dist-info/top_level.txt
apachecn_javaweb_zh_pt3-2022.10.16.0.dist-info/RECORD
